<?xml version='1.0' encoding='utf-8'?>
<osgb:OSIMSupplierMetadata xmlns:osgb="http://www.ordnancesurvey.co.uk/xml/namespaces/osgb" xmlns:xsi="http://www.w3.org/2001/XMLSchema-instance" xsi:schemaLocation="http://www.ordnancesurvey.co.uk/xml/namespaces/osgb OSIMSupplierMetadata.xsd"><osgb:copyright>Copyright Getmapping Plc 2004 - 2019</osgb:copyright><osgb:kmReference>SD4870</osgb:kmReference><osgb:dateFlown>22/06/2018</osgb:dateFlown><osgb:dateFlown>18/10/2018</osgb:dateFlown><osgb:kmRectangle><osgb:Rectangle srsName="osgb:BNG"><gml:coordinates xmlns:gml="http://www.opengis.net/gml">348000,470000 349000,471000</gml:coordinates></osgb:Rectangle></osgb:kmRectangle><osgb:lensFocalLength uom="http://www.ordnancesurvey.co.uk/xml/resource/units.xml#millimetres">100.5</osgb:lensFocalLength><osgb:nominalFlyingHeight uom="http://www.ordnancesurvey.co.uk/xml/resource/units.xml#metres">2843</osgb:nominalFlyingHeight><osgb:nominalImageScale>1:28289</osgb:nominalImageScale><osgb:resolution uom="http://www.ordnancesurvey.co.uk/xml/resource/units.xml#metres">0.25</osgb:resolution><osgb:filesize uom="http://www.ordnancesurvey.co.uk/xml/resource/units.xml#MegaBytes">12.693</osgb:filesize><osgb:control>GPS and OSTN02</osgb:control><osgb:createdBy>Imagery sourced from Getmapping Plc</osgb:createdBy><osgb:correctionType>Orthorectified</osgb:correctionType><osgb:dateOfCompletion>27/02/2019</osgb:dateOfCompletion></osgb:OSIMSupplierMetadata>